process/__init__.py
process/constants.py
process/process.py
process/py.typed
process/types.py
process/utils.py
process/asyncio/__init__.py
process/asyncio/constants.py
process/asyncio/process.py
process/asyncio/types.py
process/core/__init__.py
process/core/constants.py
process/core/errors.py
process/core/process.py
process/core/protocol.py
process/core/types.py
tests/__init__.py
tests/conftest.py
tests/test_errors.py
tests/test_process.py
tests/asyncio/__init__.py
tests/asyncio/test_errors.py
tests/asyncio/test_process.py
python_process-1.0.15.dist-info/LICENSE
python_process-1.0.15.dist-info/METADATA
python_process-1.0.15.dist-info/WHEEL
python_process-1.0.15.dist-info/top_level.txt
python_process-1.0.15.dist-info/RECORD
